[
    {
        "words": [
            [
                "구두",
                "가죽이나 인조 가죽 따위로 만든 신발."
            ],
            [
                "구두",
                "말로 하는 것."
            ]
        ],
        "subDescription": "http://sldict.korean.go.kr/multimedia/multimedia_files/convert/20200820/732310/MOV000249998_700X466.mp4",
        "regDate": "2023-05-24 11:04:42"
    },
    {
        "words": [
            [
                "산수",
                "자연의 산과 물이 어우러진 경치."
            ],
            [
                "산수",
                "초등학교 과정에서 덧셈과 뺄셈, 곱셈과 나눗셈을 다루는 기초적인 수학."
            ]
        ],
        "subDescription": "http://sldict.korean.go.kr/multimedia/multimedia_files/convert/20160924/345873/MOV000244828_700X466.mp4",
        "regDate": "2023-05-24 11:04:43"
    },
    {
        "words": [
            [
                "만",
                " 일정한 수효나 양의 끝에서 더 할 수 없는 상태."
            ],
            [
                "만",
                " 오직 그것뿐이고 다른 것은 없는 상태."
            ],
            [
                "만",
                " 어떤 일에 대해 특별히 구별하거나, 다르게 취급하는 상태."
            ]
        ],
        "subDescription": "http://sldict.korean.go.kr/multimedia/multimedia_files/convert/20220727/1001911/MOV000359488_700X466.mp4",
        "regDate": "2023-05-24 11:04:43"
    },
    {
        "words": [
            [
                "걸리다",
                "무엇이 장애물에 닿아 멈추거나 느려지다."
            ],
            [
                "걸리다",
                "병에 감염되다."
            ],
            [
                "걸리다",
                "법이나 규칙에 저촉되다."
            ]
        ],
        "subDescription": "http://sldict.korean.go.kr/multimedia/multimedia_files/convert/20221021/1043090/MOV000361064_700X466.mp4",
        "regDate": "2023-05-24 11:04:43"
    },
    {
        "words": [
            [
                "두드러지다",
                "겉으로 뚜렷하게 드러나다."
            ],
            [
                "두드러지다",
                "주위보다 뛰어나게 두각을 나타내다."
            ],
            [
                "두드러지다",
                "피부에 불규칙하게 도드라진 발진이 생기다."
            ]
        ],
        "subDescription": "http://sldict.korean.go.kr/multimedia/multimedia_files/convert/20201210/784461/MOV000356891_700X466.mp4",
        "regDate": "2023-05-24 11:04:43"
    },
    {
        "words": [
            [
                "익히다",
                "음식이나 재료를 적당한 열로 처리하여 먹을 수 있게 만들다."
            ],
            [
                "익히다",
                "경험 등을 통해 능숙하게 만들다."
            ]
        ],
        "subDescription": "http://sldict.korean.go.kr/multimedia/multimedia_files/convert/20200824/734831/MOV000256980_700X466.mp4",
        "regDate": "2023-05-24 11:04:43"
    },
    {
        "words": [
            [
                "목메다",
                "감정이 복받쳐 목소리가 잘 나오지 않다."
            ],
            [
                "목메다",
                "목을 졸라 숨통이 막히다."
            ]
        ],
        "subDescription": "http://sldict.korean.go.kr/multimedia/multimedia_files/convert/20220812/1010159/MOV000360139_700X466.mp4",
        "regDate": "2023-05-24 11:04:43"
    },
    {
        "words": [
            [
                "적 없다",
                "어떤 일을 해 본 경험이 없다."
            ],
            [
                "적 없다",
                "적이 없는 상태."
            ]
        ],
        "subDescription": "http://sldict.korean.go.kr/multimedia/multimedia_files/convert/20200821/733028/MOV000259712_700X466.mp4",
        "regDate": "2023-05-24 11:04:43"
    },
    {
        "words": [
            [
                "농",
                "농사를 짓는 일. 또는 농사짓는 방법."
            ],
            [
                "농",
                "재미있게 하는 말이나 행동으로 사람을 웃기는 일."
            ]
        ],
        "subDescription": "http://sldict.korean.go.kr/multimedia/multimedia_files/convert/20220801/1004802/MOV000359714_700X466.mp4",
        "regDate": "2023-05-24 11:04:43"
    },
    {
        "words": [
            [
                "신부",
                "결혼하는 여자."
            ],
            [
                "신부",
                "성직자로서 예식을 집행하는 사람."
            ]
        ],
        "subDescription": "http://sldict.korean.go.kr/multimedia/multimedia_files/convert/20200821/733330/MOV000257147_700X466.mp4",
        "regDate": "2023-05-24 11:04:43"
    },
    {
        "words": [
            [
                "수입",
                "외국으로부터 물건이나 상품을 사들임."
            ],
            [
                "수입",
                "일정 기간 동안 개인이나 기관이 벌어들인 돈."
            ]
        ],
        "subDescription": "http://sldict.korean.go.kr/multimedia/multimedia_files/convert/20220802/1005882/MOV000359884_700X466.mp4",
        "regDate": "2023-05-24 11:04:44"
    },
    {
        "words": [
            [
                "킬로",
                "킬로그램의 약칭, 무게의 단위."
            ],
            [
                "킬로",
                "킬로미터의 약칭, 거리의 단위."
            ]
        ],
        "subDescription": "http://sldict.korean.go.kr/multimedia/multimedia_files/convert/20220801/1004510/MOV000359659_700X466.mp4",
        "regDate": "2023-05-24 11:04:44"
    },
    {
        "words": [
            [
                "위",
                "공간적으로 높거나 높은 곳에 있는 상태."
            ],
            [
                "위",
                "사물의 상부 또는 바깥쪽 면."
            ],
            [
                "위",
                "사람의 몸 안에 음식을 저장하고 소화하는 기관."
            ]
        ],
        "subDescription": "http://sldict.korean.go.kr/multimedia/multimedia_files/convert/20200820/732405/MOV000255624_700X466.mp4",
        "regDate": "2023-05-24 11:04:44"
    },
    {
        "words": [
            [
                "주교",
                "가톨릭교에서 교구를 다스리는 성직자."
            ],
            [
                "주교",
                "일부 그리스도교에서 교회를 감독하는 직책을 가진 사람."
            ]
        ],
        "subDescription": "http://sldict.korean.go.kr/multimedia/multimedia_files/convert/20221018/1042011/MOV000360928_700X466.mp4",
        "regDate": "2023-05-24 11:04:44"
    },
    {
        "words": [
            [
                "파",
                "대파, 쪽파 등의 식물로, 요리에 쓰이는 향신채. "
            ],
            [
                "파",
                "조직이나 단체 따위가 갈라진 부분."
            ],
            [
                "파",
                "물결이 치는 현상."
            ]
        ],
        "subDescription": "http://sldict.korean.go.kr/multimedia/multimedia_files/convert/20200825/735469/MOV000234826_700X466.mp4",
        "regDate": "2023-05-24 11:04:44"
    },
    {
        "words": [
            [
                "중위",
                "군대 계급 중의 하나로, 소위의 위, 대위의 아래에 해당하는 계급."
            ],
            [
                "중위",
                "어떤 서열이나 계층에서 중간에 해당하는 위치."
            ]
        ],
        "subDescription": "http://sldict.korean.go.kr/multimedia/multimedia_files/convert/20220727/1001893/MOV000359470_700X466.mp4",
        "regDate": "2023-05-24 11:04:44"
    },
    {
        "words": [
            [
                "중장",
                "장성 계급의 하나로 대장의 아래, 소장의 위입니다."
            ],
            [
                "중장",
                "중간 수준의 무거운 장비를 사용하여 건설 및 토목 공사를 수행하는 작업."
            ]
        ],
        "subDescription": "http://sldict.korean.go.kr/multimedia/multimedia_files/convert/20220727/1001895/MOV000359472_700X466.mp4",
        "regDate": "2023-05-24 11:04:44"
    },
    {
        "words": [
            [
                "걷히다",
                "구름이나 안개 따위가 없어져서 날이 맑다."
            ],
            [
                "걷히다",
                "빚이나 세금 따위가 거두어지다."
            ],
            [
                "걷히다",
                "병이나 기운 따위가 없어지다."
            ]
        ],
        "subDescription": "http://sldict.korean.go.kr/multimedia/multimedia_files/convert/20200825/735774/MOV000240541_700X466.mp4",
        "regDate": "2023-05-24 11:04:44"
    },
    {
        "words": [
            [
                "실각",
                "권력이나 지위를 잃고 떨어짐."
            ],
            [
                "실각",
                "사람이 발을 헛디뎌 넘어짐."
            ]
        ],
        "subDescription": "http://sldict.korean.go.kr/multimedia/multimedia_files/convert/20220727/1001924/MOV000359501_700X466.mp4",
        "regDate": "2023-05-24 11:04:44"
    },
    {
        "words": [
            [
                "조합",
                "공동의 목적을 이루기 위해 결성한 단체."
            ],
            [
                "조합",
                "여러 가지를 한데 모으거나 합침."
            ]
        ],
        "subDescription": "http://sldict.korean.go.kr/multimedia/multimedia_files/convert/20221017/1041518/MOV000360797_700X466.mp4",
        "regDate": "2023-05-24 11:04:45"
    },
    {
        "words": [
            [
                "북도",
                "한국 전통 악기로서, 북을 두드려서 소리를 내는 행위."
            ],
            [
                "북도",
                "도자기 만드는 과정에서 사용되는 전통적인 도구."
            ],
            [
                "북도",
                "북쪽에 위치한 지역이나 도를 의미하는 단어."
            ]
        ],
        "subDescription": "http://sldict.korean.go.kr/multimedia/multimedia_files/convert/20221012/1038766/MOV000360230_700X466.mp4",
        "regDate": "2023-05-24 11:04:45"
    },
    {
        "words": [
            [
                "외상",
                "몸의 겉부분에 입은 상처."
            ],
            [
                "외상",
                "외상 매출 또는 외상 판매 거래에서 물품을 미리 받고 대금을 나중에 치르는 일."
            ],
            [
                "외상",
                "심하게 놀라거나 충격을 받은 심리 상태."
            ]
        ],
        "subDescription": "http://sldict.korean.go.kr/multimedia/multimedia_files/convert/20200825/735651/MOV000256939_700X466.mp4",
        "regDate": "2023-05-24 11:04:46"
    },
    {
        "words": [
            [
                "전주",
                "한국의 도시 중 하나로, 전라북도의 도청 소재지."
            ],
            [
                "전주",
                "음악에서 곡이 시작되기 전에 연주되는 부분."
            ]
        ],
        "subDescription": "http://sldict.korean.go.kr/multimedia/multimedia_files/convert/20221014/1040233/MOV000360671_700X466.mp4",
        "regDate": "2023-05-24 11:04:46"
    },
    {
        "words": [
            [
                "분수",
                "수학에서, 하나의 수를 다른 수로 나눈 비율을 나타내는 숫자 표현."
            ],
            [
                "분수",
                "땅속에 묻힌 물이 솟아오르는 샘."
            ]
        ],
        "subDescription": "http://sldict.korean.go.kr/multimedia/multimedia_files/convert/20200825/735513/MOV000239731_700X466.mp4",
        "regDate": "2023-05-24 11:04:46"
    },
    {
        "words": [
            [
                "뻔하다",
                "분명할 정도로 확실하다."
            ],
            [
                "뻔하다",
                "어떤 일이 일어날 뻔하다."
            ]
        ],
        "subDescription": "http://sldict.korean.go.kr/multimedia/multimedia_files/convert/20200824/735050/MOV000253653_700X466.mp4",
        "regDate": "2023-05-24 11:04:46"
    },
    {
        "words": [
            [
                "매장",
                "물건을 파는 가게."
            ],
            [
                "매장",
                "시체를 무덤에 묻는 것."
            ],
            [
                "매장",
                "어떤 사람이나 사물을 사회적으로 완전히 제거하거나 소외시키는 것."
            ]
        ],
        "subDescription": "http://sldict.korean.go.kr/multimedia/multimedia_files/convert/20200824/735061/MOV000250661_700X466.mp4",
        "regDate": "2023-05-24 11:04:46"
    },
    {
        "words": [
            [
                "부유",
                "재산이 넉넉하게 많은 상태."
            ],
            [
                "부유",
                "물 위나 공중에 떠다님."
            ]
        ],
        "subDescription": "http://sldict.korean.go.kr/multimedia/multimedia_files/convert/20191021/629531/MOV000254468_700X466.mp4",
        "regDate": "2023-05-24 11:04:47"
    },
    {
        "words": [
            [
                "김",
                "밭이나 들에서 자라는 곡식이나 풀이 잘 자라도록 잡초를 뽑는 일."
            ],
            [
                "김",
                "조미료나 간식으로 쓰이는 해조류."
            ],
            [
                "김",
                "한국에서 흔히 볼 수 있는 성씨 중 하나."
            ]
        ],
        "subDescription": "http://sldict.korean.go.kr/multimedia/multimedia_files/convert/20200821/733132/MOV000250022_700X466.mp4",
        "regDate": "2023-05-24 11:04:47"
    },
    {
        "words": [
            [
                "배",
                "먹을 수 있는 과일 중 하나로, 나무에서 자라고 주로 달고 즙이 많은 것이 특징이다."
            ],
            [
                "배",
                "사람이나 짐을 운반하는 데 사용하는 해상 교통수단."
            ],
            [
                "배",
                "사람 또는 동물의 신체 중 아랫배 부분 또는 그 근처."
            ]
        ],
        "subDescription": "http://sldict.korean.go.kr/multimedia/multimedia_files/convert/20191017/628477/MOV000254717_700X466.mp4",
        "regDate": "2023-05-24 11:04:47"
    },
    {
        "words": [
            [
                "사신",
                "나라의 명령을 받아 다른 나라에 파견되는 외교 임무를 맡은 사람."
            ],
            [
                "사신",
                "죽음을 뜻하는 의인화된 존재."
            ]
        ],
        "subDescription": "http://sldict.korean.go.kr/multimedia/multimedia_files/convert/20221107/1049653/MOV000361252_700X466.mp4",
        "regDate": "2023-05-24 11:04:47"
    },
    {
        "words": [
            [
                "따르다",
                "사람이나 사물의 뒤를 이어가거나 뒤를 따라 움직이다."
            ],
            [
                "따르다",
                "그릇을 기울여 안에 들어 있는 액체를 밖으로 조금씩 흐르게 하다."
            ],
            [
                "따르다",
                "어떤 의견을 받아들이거나 그에 따르다."
            ]
        ],
        "subDescription": "http://sldict.korean.go.kr/multimedia/multimedia_files/convert/20200821/733705/MOV000239609_700X466.mp4",
        "regDate": "2023-05-24 11:04:47"
    },
    {
        "words": [
            [
                "강도",
                "남의 것을 억지로 빼앗는 도둑."
            ],
            [
                "강도",
                "물건 따위의 단단하고 질긴 정도."
            ]
        ],
        "subDescription": "http://sldict.korean.go.kr/multimedia/multimedia_files/convert/20160325/248636/MOV000261962_700X466.mp4",
        "regDate": "2023-05-24 11:04:47"
    },
    {
        "words": [
            [
                "배다",
                "물체에 배어 있는 액체나 기체가 빠져나오다."
            ],
            [
                "배다",
                "어떤 감정이나 생각 따위가 깊이 스며 들어 자리를 잡다."
            ],
            [
                "배다",
                "여자가 아이를 가지다."
            ]
        ],
        "subDescription": "http://sldict.korean.go.kr/multimedia/multimedia_files/convert/20200825/735736/MOV000244932_700X466.mp4",
        "regDate": "2023-05-24 11:04:48"
    },
    {
        "words": [
            [
                "센터",
                "중심이 되는 장소나 시설."
            ],
            [
                "센터",
                "농구에서, 팀의 중앙을 담당하는 포지션."
            ]
        ],
        "subDescription": "http://sldict.korean.go.kr/multimedia/multimedia_files/convert/20191022/630030/MOV000254384_700X466.mp4",
        "regDate": "2023-05-24 11:04:48"
    },
    {
        "words": [
            [
                "이",
                "사람이 가지고 있는 뼈로 된 하얀 물질로, 음식을 씹는 데 사용된다."
            ],
            [
                "이",
                "한글 자음의 하나로, 알파벳으로는 'L'에 해당하는 소리."
            ],
            [
                "이",
                "일부 과일이나 식물의 가장자리에 돋은 작은 돌기."
            ]
        ],
        "subDescription": "http://sldict.korean.go.kr/multimedia/multimedia_files/convert/20160325/264676/MOV000270507_700X466.mp4",
        "regDate": "2023-05-24 11:04:48"
    },
    {
        "words": [
            [
                "공주",
                "충청남도에 있는 도시."
            ],
            [
                "공주",
                "왕의 딸."
            ]
        ],
        "subDescription": "http://sldict.korean.go.kr/multimedia/multimedia_files/convert/20221014/1039981/MOV000360525_700X466.mp4",
        "regDate": "2023-05-24 11:04:48"
    },
    {
        "words": [
            [
                "상",
                "어떤 일이나 경기에서 뛰어난 성적을 세운 사람에게 주는 물건이나 증서."
            ],
            [
                "상",
                "사고나 병 등으로 남은 흉터나 흔적."
            ],
            [
                "상",
                "사람이 사망한 것에 대해 슬퍼하며 치르는 의식."
            ]
        ],
        "subDescription": "http://sldict.korean.go.kr/multimedia/multimedia_files/convert/20191018/628558/MOV000254775_700X466.mp4",
        "regDate": "2023-05-24 11:04:48"
    },
    {
        "words": [
            [
                "조수",
                "주로 수업이나 연구 따위의 활동을 보조하는 사람."
            ],
            [
                "조수",
                "고래, 돌고래, 물고기 등 바다에서 서식하는 생물."
            ],
            [
                "조수",
                "해변에서 주기적으로 밀려오는 물의 움직임."
            ]
        ],
        "subDescription": "http://sldict.korean.go.kr/multimedia/multimedia_files/convert/20200820/732471/MOV000259087_700X466.mp4",
        "regDate": "2023-05-24 11:04:48"
    },
    {
        "words": [
            [
                "목자",
                "양이나 소를 기르는 사람."
            ],
            [
                "목자",
                "종교에서, 신도들을 이끄는 사람."
            ]
        ],
        "subDescription": "http://sldict.korean.go.kr/multimedia/multimedia_files/convert/20220801/1004800/MOV000359712_700X466.mp4",
        "regDate": "2023-05-24 11:04:48"
    },
    {
        "words": [
            [
                "집사",
                "교회의 재정과 관련된 일을 맡아보는 사람."
            ],
            [
                "집사",
                "주인 가까이 있으면서 그 집 일을 맡아보는 사람."
            ]
        ],
        "subDescription": "http://sldict.korean.go.kr/multimedia/multimedia_files/convert/20160325/285293/MOV000284234_700X466.mp4",
        "regDate": "2023-05-24 11:04:48"
    },
    {
        "words": [
            [
                "첩",
                "본처 외에 정부(情婦)로 맞아들인 여자."
            ],
            [
                "첩",
                "스파이로 활동하는 사람."
            ]
        ],
        "subDescription": "http://sldict.korean.go.kr/multimedia/multimedia_files/convert/20200825/735666/MOV000258297_700X466.mp4",
        "regDate": "2023-05-24 11:04:49"
    },
    {
        "words": [
            [
                "부정",
                "어떤 사실이나 생각, 상황 등을 그렇지 않다고 하는 것."
            ],
            [
                "부정",
                "바르지 않거나 옳지 못함."
            ]
        ],
        "subDescription": "http://sldict.korean.go.kr/multimedia/multimedia_files/convert/20200821/732869/MOV000254482_700X466.mp4",
        "regDate": "2023-05-24 11:04:49"
    },
    {
        "words": [
            [
                "취하다",
                "술·마약 등에 물려서 정상적인 상태를 잃다."
            ],
            [
                "취하다",
                "어떤 상황이나 상태에 젖어 들다."
            ],
            [
                "취하다",
                "자기 것으로 받아들이다."
            ]
        ],
        "subDescription": "http://sldict.korean.go.kr/multimedia/multimedia_files/convert/20200824/735079/MOV000259608_700X466.mp4",
        "regDate": "2023-05-24 11:04:49"
    },
    {
        "words": [
            [
                "유지",
                "어떤 상태나 상황이 변하지 않도록 계속함."
            ],
            [
                "유지",
                "사회적으로 널리 알려지고 존경받는 사람."
            ],
            [
                "유지",
                "기름이 많은 액체."
            ]
        ],
        "subDescription": "http://sldict.korean.go.kr/multimedia/multimedia_files/convert/20220801/1004606/MOV000359686_700X466.mp4",
        "regDate": "2023-05-24 11:04:49"
    },
    {
        "words": [
            [
                "-전",
                "공간적으로 앞이라는 뜻을 더하는 접미사."
            ],
            [
                "-전",
                "수량적이나 시간적으로 앞이라는 뜻을 더하는 접미사."
            ]
        ],
        "subDescription": "http://sldict.korean.go.kr/multimedia/multimedia_files/convert/20221012/1038757/MOV000360222_700X466.mp4",
        "regDate": "2023-05-24 11:04:49"
    },
    {
        "words": [
            [
                "만",
                "어떤 기준에 차거나 어떤 일이 일어난 시점. 예: '이 일은 이제 만 3년이 되었다.'"
            ],
            [
                "만",
                "수량을 나타내는 단위. 예: '만 원', '만 명'"
            ]
        ],
        "subDescription": "http://sldict.korean.go.kr/multimedia/multimedia_files/convert/20220802/1005859/MOV000359861_700X466.mp4",
        "regDate": "2023-05-24 11:04:49"
    },
    {
        "words": [
            [
                "대가",
                " 어떤 분야에서 뛰어난 능력을 가진 사람."
            ],
            [
                "대가",
                "무엇에 대한 보상으로 치르는 비용."
            ]
        ],
        "subDescription": "http://sldict.korean.go.kr/multimedia/multimedia_files/convert/20200824/735250/MOV000260410_700X466.mp4",
        "regDate": "2023-05-24 11:04:49"
    },
    {
        "words": [
            [
                "대모",
                "어떤 사건에 대규모로 참여하는 것을 이르는 말. 특히 시위나 집회 등을 가리킴."
            ],
            [
                "대모",
                "부모를 대신하여 아이를 보살펴 주는 역할을 하는 여자."
            ]
        ],
        "subDescription": "http://sldict.korean.go.kr/multimedia/multimedia_files/convert/20221018/1041777/MOV000360838_700X466.mp4",
        "regDate": "2023-05-24 11:04:50"
    },
    {
        "words": [
            [
                "장로",
                "개신교에서, 교회 운영을 담당하는 평신도 중 책임자."
            ],
            [
                "장로",
                " 나이가 많고 학문과 덕이 높은 사람."
            ],
            [
                "장로",
                "배움이 크고 나이가 많으며 덕이 높은 승려를 높여 이르는 말."
            ]
        ],
        "subDescription": "http://sldict.korean.go.kr/multimedia/multimedia_files/convert/20160325/285192/MOV000283894_700X466.mp4",
        "regDate": "2023-05-24 11:04:48"
    },
    {
        "words": [
            [
                "장기",
                "사람의 몸속에 있는 내장 기관."
            ],
            [
                "장기",
                "도자기 등을 장식하는 기법의 하나."
            ],
            [
                "장기",
                "나무로 만든 32짝의 말을 붉은 글자와 푸른 글자의 두 종류로 나누어 판 위에 벌여 놓고 서로 번갈아 가며 공격과 수비를 교대로 하여 승부를 가리는 놀이. 또는 그런 놀이를 하는 데 쓰는 기구."
            ]
        ],
        "subDescription": "http://sldict.korean.go.kr/multimedia/multimedia_files/convert/20201229/792739/MOV000357962_700X466.mp4",
        "regDate": "2023-05-24 11:04:48"
    }
]